portfolio_carousel/__init__.py
portfolio_carousel/frontend/index.html
portfolio_carousel/frontend/css/style.css
portfolio_carousel/frontend/css/swiper-bundle.min.css
portfolio_carousel/frontend/images/b2b.jpg
portfolio_carousel/frontend/images/tracking.jpg
portfolio_carousel/frontend/images/zenk.jpg
portfolio_carousel/frontend/js/main.js
portfolio_carousel/frontend/js/script.js
portfolio_carousel/frontend/js/streamlit-component-lib.js
portfolio_carousel/frontend/js/swiper-bundle.min.js
portfolio_carousel-0.1.5.dist-info/LICENSE
portfolio_carousel-0.1.5.dist-info/METADATA
portfolio_carousel-0.1.5.dist-info/WHEEL
portfolio_carousel-0.1.5.dist-info/top_level.txt
portfolio_carousel-0.1.5.dist-info/RECORD
